lox/__init__.py
lox/main.py
lox/master.py
lox/recovery.py
lox/utils.py
lox/vault.py
loxword-0.0.4.dist-info/licenses/LICENSE
loxword-0.0.4.dist-info/METADATA
loxword-0.0.4.dist-info/WHEEL
loxword-0.0.4.dist-info/entry_points.txt
loxword-0.0.4.dist-info/top_level.txt
loxword-0.0.4.dist-info/RECORD
