Metadata-Version: 2.4
Name: loxword
Version: 0.0.4
Summary: A secure CLI password manager with multi-user support and auto-lock features.
Author-email: Aditya Chavan <iaditya.2016@gmail.com>
License: MIT
Project-URL: Homepage, https://github.com/adchad90/Lox
Project-URL: Issues, https://github.com/adchad90/Lox/issues
Project-URL: Repository, https://github.com/adchad90/Lox.git
Keywords: password,manager,security,cli,encryption,vault,bcrypt
Classifier: Development Status :: 4 - Beta
Classifier: Intended Audience :: End Users/Desktop
Classifier: License :: OSI Approved :: MIT License
Classifier: Operating System :: OS Independent
Classifier: Programming Language :: Python :: 3
Classifier: Programming Language :: Python :: 3.7
Classifier: Programming Language :: Python :: 3.8
Classifier: Programming Language :: Python :: 3.9
Classifier: Programming Language :: Python :: 3.10
Classifier: Programming Language :: Python :: 3.11
Classifier: Programming Language :: Python :: 3.12
Classifier: Programming Language :: Python :: 3.13
Classifier: Topic :: Security
Classifier: Topic :: Utilities
Classifier: Environment :: Console
Classifier: Topic :: Security :: Cryptography
Requires-Python: >=3.7
License-File: LICENSE
Requires-Dist: cryptography<44.0.0,>=39.0.0
Requires-Dist: bcrypt<5.0.0,>=4.0.0
Requires-Dist: pyperclip<2.0.0,>=1.8.0
Dynamic: license-file
